{"name":"Incorrect Login","id":"login-user;incorrect-login","testSteps":[{"number":1,"description":"Given the user is on the login screen","duration":11827,"startTime":"2023-06-07T20:20:28.883860-05:00[America/Bogota]","screenshots":[{"screenshot":"e5a62e73033ac70a97a0587beb4e291603e663dbcf08fb41a0ff94d23e0894e5.png","timeStamp":1686187240711}],"result":"SUCCESS","precondition":false,"level":0,"children":[{"number":2,"description":"Jhon navigate to","duration":4389,"startTime":"2023-06-07T20:20:36.309246-05:00[America/Bogota]","screenshots":[{"screenshot":"598ff64e850c5c1bb5ee67d406beb0694b4266d8217d0db106804894bead8f1c.png","timeStamp":1686187237213},{"screenshot":"e5a62e73033ac70a97a0587beb4e291603e663dbcf08fb41a0ff94d23e0894e5.png","timeStamp":1686187240698}],"result":"SUCCESS","precondition":false,"level":1,"children":[{"number":3,"description":"Jhon clicks on  Button Login","duration":3470,"startTime":"2023-06-07T20:20:37.217369-05:00[America/Bogota]","screenshots":[{"screenshot":"598ff64e850c5c1bb5ee67d406beb0694b4266d8217d0db106804894bead8f1c.png","timeStamp":1686187237239},{"screenshot":"e5a62e73033ac70a97a0587beb4e291603e663dbcf08fb41a0ff94d23e0894e5.png","timeStamp":1686187240675},{"screenshot":"e5a62e73033ac70a97a0587beb4e291603e663dbcf08fb41a0ff94d23e0894e5.png","timeStamp":1686187240687}],"result":"SUCCESS","precondition":false,"level":2}]}]},{"number":4,"description":"When they enter incorrect credentials","duration":9457,"startTime":"2023-06-07T20:20:40.712381-05:00[America/Bogota]","screenshots":[{"screenshot":"482c654f5a05ad34020e64edfb0d55cdd129f81c0dd6c50f08ec428e9e0a87f1.png","timeStamp":1686187250169}],"result":"SUCCESS","precondition":false,"level":0,"children":[{"number":5,"description":"Jhon enters \u0027prueba@accenture.com\u0027 into Input email","duration":2333,"startTime":"2023-06-07T20:20:40.734340-05:00[America/Bogota]","screenshots":[{"screenshot":"a2967c9b18abedb5ae0726677abb27b201d58ac9edcd0e8a86b915f1b18576c1.png","timeStamp":1686187241254},{"screenshot":"3eb084b84fa0698f8ba31dbc79e080ad27d72c329463bd19b4b55eec9d8499ea.png","timeStamp":1686187243053},{"screenshot":"3eb084b84fa0698f8ba31dbc79e080ad27d72c329463bd19b4b55eec9d8499ea.png","timeStamp":1686187243067}],"result":"SUCCESS","precondition":false,"level":1},{"number":6,"description":"Jhon enters \u00271234567\u0027 into Input password","duration":1736,"startTime":"2023-06-07T20:20:43.073135-05:00[America/Bogota]","screenshots":[{"screenshot":"3eb084b84fa0698f8ba31dbc79e080ad27d72c329463bd19b4b55eec9d8499ea.png","timeStamp":1686187243096},{"screenshot":"a88e6bcb367d4fef895ac4155eaadda909501638aee90c72131a27fc4dbbccf5.png","timeStamp":1686187244796},{"screenshot":"a88e6bcb367d4fef895ac4155eaadda909501638aee90c72131a27fc4dbbccf5.png","timeStamp":1686187244809}],"result":"SUCCESS","precondition":false,"level":1},{"number":7,"description":"Jhon clicks on Button Sign In","duration":4514,"startTime":"2023-06-07T20:20:44.814582-05:00[America/Bogota]","screenshots":[{"screenshot":"a88e6bcb367d4fef895ac4155eaadda909501638aee90c72131a27fc4dbbccf5.png","timeStamp":1686187244827},{"screenshot":"b8dbe57b9e2e0aa045dbf9bd9092dc2dba2661dce373d9fabef46711b9433169.png","timeStamp":1686187249284},{"screenshot":"b8dbe57b9e2e0aa045dbf9bd9092dc2dba2661dce373d9fabef46711b9433169.png","timeStamp":1686187249328}],"result":"SUCCESS","precondition":false,"level":1}]},{"number":8,"description":"Then an error message should be displayed","duration":2088,"startTime":"2023-06-07T20:20:50.173026-05:00[America/Bogota]","screenshots":[{"screenshot":"482c654f5a05ad34020e64edfb0d55cdd129f81c0dd6c50f08ec428e9e0a87f1.png","timeStamp":1686187252261}],"result":"SUCCESS","precondition":false,"level":0,"children":[{"number":9,"description":"Then logged incorrect questions","duration":2053,"startTime":"2023-06-07T20:20:50.194711-05:00[America/Bogota]","screenshots":[{"screenshot":"482c654f5a05ad34020e64edfb0d55cdd129f81c0dd6c50f08ec428e9e0a87f1.png","timeStamp":1686187252247}],"result":"SUCCESS","precondition":false,"level":1}]}],"userStory":{"id":"login-user","storyName":"Login User","displayName":"Login User","path":"login/userLogin.feature","type":"feature"},"featureTag":{"name":"Login/Login User","type":"feature","displayName":"Login/Login User"},"title":"Incorrect Login","description":"","tags":[{"name":"Login/Login User","type":"feature","displayName":"Login User"},{"name":"Login","type":"capability","displayName":"Login"}],"startTime":"2023-06-07T20:20:28.875558-05:00[America/Bogota]","duration":23388,"projectKey":"","sessionId":"9f84e44a-f9e4-4924-b729-9d7baabdaa24","driver":"appium:jhon","isManualTestingUpToDate":false,"manual":false,"testSource":"Cucumber","actors":[{"name":"Jhon","can":["browse the web"]}],"result":"SUCCESS"}